glint_mask_tools/__init__.py
glint_mask_tools/band_alignment.py
glint_mask_tools/cli.py
glint_mask_tools/glint_algorithms.py
glint_mask_tools/image_loaders.py
glint_mask_tools/maskers.py
glint_mask_tools/sensors.py
glint_mask_tools/utils.py
glint_mask_tools-4.0.0.dist-info/METADATA
glint_mask_tools-4.0.0.dist-info/WHEEL
glint_mask_tools-4.0.0.dist-info/entry_points.txt
glint_mask_tools-4.0.0.dist-info/licenses/LICENSE
glint_mask_tools-4.0.0.dist-info/RECORD
