Metadata-Version: 2.4
Name: glint-mask-tools
Version: 4.0.0
Summary: Create masks for specular reflection in UAV and aerial imagery
Author-email: Taylor Denouden <taylor.denouden@hakai.org>
License-Expression: MIT
License-File: LICENSE
Requires-Python: >=3.9
Requires-Dist: imagecodecs>=2024.12.30
Requires-Dist: loguru>=0.7.3
Requires-Dist: numpy>=2.0.2
Requires-Dist: opencv-python-headless>=4.8.0
Requires-Dist: pillow>=11.2.1
Requires-Dist: pyqt6>=6.9.1
Requires-Dist: scipy>=1.13.1
Requires-Dist: tifffile>=2024.8.30
Requires-Dist: tqdm>=4.67.1
Requires-Dist: typer>=0.16.0
